{"nodes": [{"id": "member_sanguk", "label": "Sanguk Jeong / Shariff (Logistics Team Lead)", "file_type": "document", "source_file": "Team_role_allocation_matrix.en.md", "source_location": null, "source_url": null, "captured_at": null, "author": null, "contributor": null}, {"id": "role_logistics_team_leader", "label": "LogisticsTeamLeader", "file_type": "concept", "source_file": "Team_role_allocation_matrix.en.md", "source_location": null, "source_url": null, "captured_at": null, "author": null, "contributor": null}, {"id": "concept_e2e_milestone_model", "label": "CONSOLIDATED-00 Milestone Model (M10~M160)", "file_type": "concept", "source_file": "Team_role_allocation_matrix.en.md", "source_location": null, "source_url": null, "captured_at": null, "author": null, "contributor": null}, {"id": "concept_routing_pattern", "label": "RoutingPattern (DIRECT/WH_ONLY/MOSB_DIRECT/WH_MOSB/MIXED)", "file_type": "concept", "source_file": "Team_role_allocation_matrix.en.md", "source_location": null, "source_url": null, "captured_at": null, "author": null, "contributor": null}, {"id": "concept_role_allocation_matrix", "label": "HVDC Logistics Team Role Allocation Matrix", "file_type": "concept", "source_file": "Team_role_allocation_matrix.en.md", "source_location": null, "source_url": null, "captured_at": null, "author": null, "contributor": null}], "edges": [{"source": "member_sanguk", "target": "role_logistics_team_leader", "relation": "implements", "confidence": "EXTRACTED", "confidence_score": 1.0, "source_file": "Team_role_allocation_matrix.en.md", "source_location": null, "weight": 1.0}, {"source": "member_sanguk", "target": "concept_role_allocation_matrix", "relation": "implements", "confidence": "EXTRACTED", "confidence_score": 1.0, "source_file": "Team_role_allocation_matrix.en.md", "source_location": null, "weight": 1.0}, {"source": "concept_role_allocation_matrix", "target": "concept_e2e_milestone_model", "relation": "references", "confidence": "EXTRACTED", "confidence_score": 1.0, "source_file": "Team_role_allocation_matrix.en.md", "source_location": null, "weight": 1.0}, {"source": "concept_role_allocation_matrix", "target": "concept_routing_pattern", "relation": "references", "confidence": "EXTRACTED", "confidence_score": 1.0, "source_file": "Team_role_allocation_matrix.en.md", "source_location": null, "weight": 1.0}, {"source": "member_sanguk", "target": "member_arvin", "relation": "references", "confidence": "EXTRACTED", "confidence_score": 1.0, "source_file": "Team_role_allocation_matrix.en.md", "source_location": null, "weight": 1.0}, {"source": "member_sanguk", "target": "member_haitham", "relation": "references", "confidence": "EXTRACTED", "confidence_score": 1.0, "source_file": "Team_role_allocation_matrix.en.md", "source_location": null, "weight": 1.0}, {"source": "member_sanguk", "target": "member_jhysn", "relation": "references", "confidence": "EXTRACTED", "confidence_score": 1.0, "source_file": "Team_role_allocation_matrix.en.md", "source_location": null, "weight": 1.0}, {"source": "member_sanguk", "target": "member_karthik", "relation": "references", "confidence": "EXTRACTED", "confidence_score": 1.0, "source_file": "Team_role_allocation_matrix.en.md", "source_location": null, "weight": 1.0}, {"source": "member_sanguk", "target": "member_ken", "relation": "references", "confidence": "EXTRACTED", "confidence_score": 1.0, "source_file": "Team_role_allocation_matrix.en.md", "source_location": null, "weight": 1.0}, {"source": "member_sanguk", "target": "member_minkyu_cha", "relation": "references", "confidence": "EXTRACTED", "confidence_score": 1.0, "source_file": "Team_role_allocation_matrix.en.md", "source_location": null, "weight": 1.0}, {"source": "member_sanguk", "target": "member_roldan", "relation": "references", "confidence": "EXTRACTED", "confidence_score": 1.0, "source_file": "Team_role_allocation_matrix.en.md", "source_location": null, "weight": 1.0}, {"source": "member_sanguk", "target": "member_ronnel", "relation": "references", "confidence": "EXTRACTED", "confidence_score": 1.0, "source_file": "Team_role_allocation_matrix.en.md", "source_location": null, "weight": 1.0}, {"source": "concept_exit_gate_pass", "target": "concept_backload", "relation": "semantically_similar_to", "confidence": "INFERRED", "confidence_score": 0.65, "source_file": "Team_role_allocation_matrix.en.md", "source_location": null, "weight": 1.0}], "hyperedges": [{"id": "hyper_e2e_milestone_flow", "label": "E2E Logistics Milestone Flow (M10~M160)", "nodes": ["member_karthik", "member_minkyu_cha", "member_arvin", "member_ken", "member_haitham", "member_jhysn", "member_ronnel", "member_roldan", "member_sanguk"], "relation": "participate_in", "confidence": "EXTRACTED", "confidence_score": 1.0, "source_file": "Team_role_allocation_matrix.en.md"}, {"id": "hyper_role_allocation", "label": "HVDC Team Role Allocation", "nodes": ["role_overseas_inbound_docs_coordinator", "role_marine_mosb_coordinator", "role_mosb_vp24_field_supervisor", "role_domestic_lpo_document_controller", "role_warehouse_execution_coordinator", "role_material_management_coordinator", "role_site_receiving_coordinator", "role_field_handling_support", "role_logistics_team_leader"], "relation": "form", "confidence": "EXTRACTED", "confidence_score": 1.0, "source_file": "Team_role_allocation_matrix.en.md"}, {"id": "hyper_gate_pass_collab", "label": "Gate/Exit Pass Multi-Owner Collaboration", "nodes": ["member_arvin", "member_roldan", "member_ken", "member_karthik"], "relation": "participate_in", "confidence": "EXTRACTED", "confidence_score": 1.0, "source_file": "Team_role_allocation_matrix.en.md"}]}